{
    "sourceFile": "frontend/lib/features/matches/presentation/screens/match_details_screen.dart",
    "activeCommit": 0,
    "commits": [
        {
            "activePatchIndex": 1,
            "patches": [
                {
                    "date": 1766327121732,
                    "content": "Index: \n===================================================================\n--- \n+++ \n"
                },
                {
                    "date": 1766335358744,
                    "content": "Index: \n===================================================================\n--- \n+++ \n@@ -1,1 +1,15 @@\n+import 'package:flutter/material.dart';\r\n \r\n+class MatchDetailsScreen extends StatelessWidget {\r\n+  final String matchId;\r\n+\r\n+  const MatchDetailsScreen({super.key, required this.matchId});\r\n+\r\n+  @override\r\n+  Widget build(BuildContext context) {\r\n+    return Scaffold(\r\n+      appBar: AppBar(title: const Text('Match Details')),\r\n+      body: Center(child: Text('Match ID: $matchId')),\r\n+    );\r\n+  }\r\n+}\r\n"
                }
            ],
            "date": 1766327121732,
            "name": "Commit-0",
            "content": "\r\n"
        }
    ]
}