{
    "sourceFile": "frontend/android/app/build.gradle.kts",
    "activeCommit": 0,
    "commits": [
        {
            "activePatchIndex": 5,
            "patches": [
                {
                    "date": 1766343570905,
                    "content": "Index: \n===================================================================\n--- \n+++ \n"
                },
                {
                    "date": 1766344209564,
                    "content": "Index: \n===================================================================\n--- \n+++ \n@@ -0,0 +1,44 @@\n+plugins {\r\n+    id(\"com.android.application\")\r\n+    id(\"kotlin-android\")\r\n+    // The Flutter Gradle Plugin must be applied after the Android and Kotlin Gradle plugins.\r\n+    id(\"dev.flutter.flutter-gradle-plugin\")\r\n+}\r\n+\r\n+android {\r\n+    namespace = \"com.example.frontend\"\r\n+    compileSdk = 36\r\n+    ndkVersion = flutter.ndkVersion\r\n+\r\n+    compileOptions {\r\n+        sourceCompatibility = JavaVersion.VERSION_11\r\n+        targetCompatibility = JavaVersion.VERSION_11\r\n+    }\r\n+\r\n+    kotlinOptions {\r\n+        jvmTarget = JavaVersion.VERSION_11.toString()\r\n+    }\r\n+\r\n+    defaultConfig {\r\n+        // TODO: Specify your own unique Application ID (https://developer.android.com/studio/build/application-id.html).\r\n+        applicationId = \"com.example.frontend\"\r\n+        // You can update the following values to match your application needs.\r\n+        // For more information, see: https://flutter.dev/to/review-gradle-config.\r\n+        minSdk = flutter.minSdkVersion\r\n+        targetSdk = 36\r\n+        versionCode = flutter.versionCode\r\n+        versionName = flutter.versionName\r\n+    }\r\n+\r\n+    buildTypes {\r\n+        release {\r\n+            // TODO: Add your own signing config for the release build.\r\n+            // Signing with the debug keys for now, so `flutter run --release` works.\r\n+            signingConfig = signingConfigs.getByName(\"debug\")\r\n+        }\r\n+    }\r\n+}\r\n+\r\n+flutter {\r\n+    source = \"../..\"\r\n+}\r\n"
                },
                {
                    "date": 1766344969261,
                    "content": "Index: \n===================================================================\n--- \n+++ \n@@ -12,8 +12,9 @@\n \r\n     compileOptions {\r\n         sourceCompatibility = JavaVersion.VERSION_11\r\n         targetCompatibility = JavaVersion.VERSION_11\r\n+        isCoreLibraryDesugaringEnabled = true\r\n     }\r\n \r\n     kotlinOptions {\r\n         jvmTarget = JavaVersion.VERSION_11.toString()\r\n@@ -41,48 +42,8 @@\n \r\n flutter {\r\n     source = \"../..\"\r\n }\r\n-plugins {\r\n-    id(\"com.android.application\")\r\n-    id(\"kotlin-android\")\r\n-    // The Flutter Gradle Plugin must be applied after the Android and Kotlin Gradle plugins.\r\n-    id(\"dev.flutter.flutter-gradle-plugin\")\r\n-}\r\n \r\n-android {\r\n-    namespace = \"com.example.frontend\"\r\n-    compileSdk = 34\r\n-    ndkVersion = flutter.ndkVersion\r\n-\r\n-    compileOptions {\r\n-        sourceCompatibility = JavaVersion.VERSION_11\r\n-        targetCompatibility = JavaVersion.VERSION_11\r\n-    }\r\n-\r\n-    kotlinOptions {\r\n-        jvmTarget = JavaVersion.VERSION_11.toString()\r\n-    }\r\n-\r\n-    defaultConfig {\r\n-        // TODO: Specify your own unique Application ID (https://developer.android.com/studio/build/application-id.html).\r\n-        applicationId = \"com.example.frontend\"\r\n-        // You can update the following values to match your application needs.\r\n-        // For more information, see: https://flutter.dev/to/review-gradle-config.\r\n-        minSdk = flutter.minSdkVersion\r\n-        targetSdk = 34\r\n-        versionCode = flutter.versionCode\r\n-        versionName = flutter.versionName\r\n-    }\r\n-\r\n-    buildTypes {\r\n-        release {\r\n-            // TODO: Add your own signing config for the release build.\r\n-            // Signing with the debug keys for now, so `flutter run --release` works.\r\n-            signingConfig = signingConfigs.getByName(\"debug\")\r\n-        }\r\n-    }\r\n+dependencies {\r\n+    coreLibraryDesugaring(\"com.android.tools:desugar_jdk_libs:2.1.4\")\r\n }\r\n-\r\n-flutter {\r\n-    source = \"../..\"\r\n-}\r\n"
                },
                {
                    "date": 1766346953928,
                    "content": "Index: \n===================================================================\n--- \n+++ \n@@ -0,0 +1,64 @@\n+plugins {\r\n+    id(\"com.android.application\")\r\n+    id(\"kotlin-android\")\r\n+    // The Flutter Gradle Plugin must be applied after the Android and Kotlin Gradle plugins.\r\n+    id(\"dev.flutter.flutter-gradle-plugin\")\r\n+}\r\n+\r\n+android {\r\n+    namespace = \"com.example.frontend\"\r\n+    compileSdk = 36\r\n+    ndkVersion = flutter.ndkVersion\r\n+\r\n+    compileOptions {\r\n+        sourceCompatibility = JavaVersion.VERSION_11\r\n+        targetCompatibility = JavaVersion.VERSION_11\r\n+        isCoreLibraryDesugaringEnabled = true\r\n+    }\r\n+\r\n+    kotlinOptions {\r\n+        jvmTarget = JavaVersion.VERSION_11.toString()\r\n+    }\r\n+\r\n+    defaultConfig {\r\n+        // TODO: Specify your own unique Application ID (https://developer.android.com/studio/build/application-id.html).\r\n+        applicationId = \"com.example.frontend\"\r\n+        // You can update the following values to match your application needs.\r\n+        // For more information, see: https://flutter.dev/to/review-gradle-config.\r\n+        minSdk = flutter.minSdkVersion\r\n+        targetSdk = 36\r\n+        versionCode = flutter.versionCode\r\n+        versionName = flutter.versionName\r\n+    }\r\n+\r\n+    buildTypes {\r\n+        release {\r\n+            // TODO: Add your own signing config for the release build.\r\n+            // Signing with the debug keys for now, so `flutter run --release` works.\r\n+            signingConfig = signingConfigs.getByName(\"debug\")\r\n+        }\r\n+    }\r\n+}\r\n+\r\n+flutter {\r\n+    source = \"../..\"\r\n+}\r\n+\r\n+dependencies {\r\n+    coreLibraryDesugaring(\"com.android.tools:desugar_jdk_libs:2.1.4\")\r\n+}\r\n+\r\n+val syncFlutterApkForFlutterTool = tasks.register<Copy>(\"syncFlutterApkForFlutterTool\") {\r\n+    val flutterBuildApkDir = File(\r\n+        rootProject.projectDir.parentFile,\r\n+        \"build/app/outputs/flutter-apk\",\r\n+    )\r\n+\r\n+    from(layout.buildDirectory.dir(\"outputs/flutter-apk\"))\r\n+    include(\"*.apk\")\r\n+    into(flutterBuildApkDir)\r\n+}\r\n+\r\n+tasks.matching { it.name == \"assembleDebug\" }.configureEach {\r\n+    finalizedBy(syncFlutterApkForFlutterTool)\r\n+}\r\n"
                },
                {
                    "date": 1766348205820,
                    "content": "Index: \n===================================================================\n--- \n+++ \n@@ -2,8 +2,10 @@\n     id(\"com.android.application\")\r\n     id(\"kotlin-android\")\r\n     // The Flutter Gradle Plugin must be applied after the Android and Kotlin Gradle plugins.\r\n     id(\"dev.flutter.flutter-gradle-plugin\")\r\n+    id(\"com.google.gms.google-services\")\r\n+    id(\"com.google.firebase.crashlytics\")\r\n }\r\n \r\n android {\r\n     namespace = \"com.example.frontend\"\r\n@@ -61,53 +63,4 @@\n \r\n tasks.matching { it.name == \"assembleDebug\" }.configureEach {\r\n     finalizedBy(syncFlutterApkForFlutterTool)\r\n }\r\n-plugins {\r\n-    id(\"com.android.application\")\r\n-    id(\"kotlin-android\")\r\n-    // The Flutter Gradle Plugin must be applied after the Android and Kotlin Gradle plugins.\r\n-    id(\"dev.flutter.flutter-gradle-plugin\")\r\n-}\r\n-\r\n-android {\r\n-    namespace = \"com.example.frontend\"\r\n-    compileSdk = 36\r\n-    ndkVersion = flutter.ndkVersion\r\n-\r\n-    compileOptions {\r\n-        sourceCompatibility = JavaVersion.VERSION_11\r\n-        targetCompatibility = JavaVersion.VERSION_11\r\n-        isCoreLibraryDesugaringEnabled = true\r\n-    }\r\n-\r\n-    kotlinOptions {\r\n-        jvmTarget = JavaVersion.VERSION_11.toString()\r\n-    }\r\n-\r\n-    defaultConfig {\r\n-        // TODO: Specify your own unique Application ID (https://developer.android.com/studio/build/application-id.html).\r\n-        applicationId = \"com.example.frontend\"\r\n-        // You can update the following values to match your application needs.\r\n-        // For more information, see: https://flutter.dev/to/review-gradle-config.\r\n-        minSdk = flutter.minSdkVersion\r\n-        targetSdk = 36\r\n-        versionCode = flutter.versionCode\r\n-        versionName = flutter.versionName\r\n-    }\r\n-\r\n-    buildTypes {\r\n-        release {\r\n-            // TODO: Add your own signing config for the release build.\r\n-            // Signing with the debug keys for now, so `flutter run --release` works.\r\n-            signingConfig = signingConfigs.getByName(\"debug\")\r\n-        }\r\n-    }\r\n-}\r\n-\r\n-flutter {\r\n-    source = \"../..\"\r\n-}\r\n-\r\n-dependencies {\r\n-    coreLibraryDesugaring(\"com.android.tools:desugar_jdk_libs:2.1.4\")\r\n-}\r\n"
                },
                {
                    "date": 1766388710957,
                    "content": "Index: \n===================================================================\n--- \n+++ \n@@ -2,12 +2,24 @@\n     id(\"com.android.application\")\r\n     id(\"kotlin-android\")\r\n     // The Flutter Gradle Plugin must be applied after the Android and Kotlin Gradle plugins.\r\n     id(\"dev.flutter.flutter-gradle-plugin\")\r\n-    id(\"com.google.gms.google-services\")\r\n-    id(\"com.google.firebase.crashlytics\")\r\n }\r\n \r\n+// Firebase Gradle plugins require `google-services.json`.\r\n+// Make them conditional so the app can still build/run without Firebase configured.\r\n+val hasGoogleServicesJson = listOf(\r\n+    file(\"google-services.json\"),\r\n+    file(\"src/google-services.json\"),\r\n+    file(\"src/debug/google-services.json\"),\r\n+    file(\"src/release/google-services.json\"),\r\n+).any { it.exists() }\r\n+\r\n+if (hasGoogleServicesJson) {\r\n+    apply(plugin = \"com.google.gms.google-services\")\r\n+    apply(plugin = \"com.google.firebase.crashlytics\")\r\n+}\r\n+\r\n android {\r\n     namespace = \"com.example.frontend\"\r\n     compileSdk = 36\r\n     ndkVersion = flutter.ndkVersion\r\n"
                }
            ],
            "date": 1766343570905,
            "name": "Commit-0",
            "content": "plugins {\r\n    id(\"com.android.application\")\r\n    id(\"kotlin-android\")\r\n    // The Flutter Gradle Plugin must be applied after the Android and Kotlin Gradle plugins.\r\n    id(\"dev.flutter.flutter-gradle-plugin\")\r\n}\r\n\r\nandroid {\r\n    namespace = \"com.example.frontend\"\r\n    compileSdk = 34\r\n    ndkVersion = flutter.ndkVersion\r\n\r\n    compileOptions {\r\n        sourceCompatibility = JavaVersion.VERSION_11\r\n        targetCompatibility = JavaVersion.VERSION_11\r\n    }\r\n\r\n    kotlinOptions {\r\n        jvmTarget = JavaVersion.VERSION_11.toString()\r\n    }\r\n\r\n    defaultConfig {\r\n        // TODO: Specify your own unique Application ID (https://developer.android.com/studio/build/application-id.html).\r\n        applicationId = \"com.example.frontend\"\r\n        // You can update the following values to match your application needs.\r\n        // For more information, see: https://flutter.dev/to/review-gradle-config.\r\n        minSdk = flutter.minSdkVersion\r\n        targetSdk = 34\r\n        versionCode = flutter.versionCode\r\n        versionName = flutter.versionName\r\n    }\r\n\r\n    buildTypes {\r\n        release {\r\n            // TODO: Add your own signing config for the release build.\r\n            // Signing with the debug keys for now, so `flutter run --release` works.\r\n            signingConfig = signingConfigs.getByName(\"debug\")\r\n        }\r\n    }\r\n}\r\n\r\nflutter {\r\n    source = \"../..\"\r\n}\r\n"
        }
    ]
}